Workbook

Sheet Cover
A1: AVIntelligence — Partner Program Economics
A2: B2B partner channel · accountants & bookkeepers · business orgs & coworking · affiliates & creators
A3: Prepared May 31, 2026 · US / North America focus · Optimizing Pro recurring revenue + paying volume
A5: WHAT'S INSIDE
A6: Assumptions | B6: All editable inputs (blue/yellow). Pricing, margin, churn, commissions, thresholds.
A7: Unit Economics | B7: LTV, LTV:CAC vs paid ads, and reward cost-vs-value.
A8: Reward Tiers | B8: The 4-tier program: Registered / Bronze / Silver / Gold; cash vs access track.
A9: 12-Month Scenarios | B9: Conservative / Base / Stretch revenue ramp with churn.
A11: HEADLINE ECONOMICS
A12: Pro price ($/mo) | B12: =Assumptions!$B$5 -> 12
A13: LTV — gross revenue | B13: ='Unit Economics'!B8 -> 171.42857
A14: Net gross profit / referred customer | B14: ='Unit Economics'!B12 -> 77.142857
A15: LTV : CAC vs paid ads | B15: ='Unit Economics'!B17 -> 2.5714286
A16: Free-access reward cost | B16: ~1% of revenue unlocked
A18: HOW TO USE / LEGEND
A19: Edit BLUE text / yellow-shaded cells in Assumptions and Scenarios to run your own numbers.
A20: BLUE = input · BLACK = formula · GREEN = links to another tab.
A21: All figures are model estimates for planning, not guarantees.

Sheet Assumptions
A1: Assumptions & Inputs
A2: Edit BLUE / yellow-shaded cells to run scenarios. Black = formulas.
A4: PRICING (current)
A5: Pro — monthly price | B5: 12 | C5: $/month
A6: Annual discount | B6: 0.3 | C6: % off monthly × 12
A7: Pro — annual price | B7: =B5*12*(1-B6) -> 100.8 | C7: $/year
A8: Pro — annual effective | B8: =B7/12 -> 8.4 | C8: $/month equivalent
A9: Day Pass / Gift Code price | B9: 6 | C9: $ per code, 24-hr full access
A11: COSTS & MARGIN
A12: COGS (% of revenue) | B12: 0.25 | C12: AI processing, storage, payment fees
A13: Gross margin | B13: =1-B12 -> 0.75 | C13: equals 1 minus COGS
A15: RETENTION
A16: Monthly churn — Pro | B16: 0.07 | C16: % of subscribers lost / month
A17: Avg customer lifetime | B17: =1/B16 -> 14.285714 | C17: months (= 1 / churn)
A19: COMMISSION & REWARDS
A20: Standard cash commission | B20: 0.3 | C20: recurring, paid for customer life
A21: Top-tier (Gold) commission | B21: 0.4 | C21: recurring
A22: Access-track residual commission | B22: 0.15 | C22: Gold cash overflow
A23: Wholesale discount (resell partners) | B23: 0.3 | C23: mirrors QuickBooks ProAdvisor 30%
A24: Wholesale Pro price | B24: =B5*(1-B23) -> 8.4 | C24: $/mo to partner
A25: Wholesale code price | B25: =B9*(1-B23) -> 4.2 | C25: $/code to partner
A27: REWARD THRESHOLDS (active paid referrals)
A28: Free 1 month Pro at | B28: 3 | C28: active paid referrals
A29: Free 6 months Pro at | B29: 10 | C29: active paid referrals
A30: Free 12 months (annual) at | B30: 25 | C30: active paid referrals
A32: CONVERSION
A33: Day Pass -> Pro conversion | B33: 0.2 | C33: % of pass users upgrading to Pro
A35: MARKET BENCHMARKS (reference only)
A36: Dext Practice (per client/mo) | B36: 17.7 | C36: Source: Dext / costbench, May 2026
A37: Dext Business (per mo) | B37: 24 | C37: Source: Dext, May 2026
A38: Expensify Collect (per user/mo) | B38: 5 | C38: Control = $9. Source: Expensify, 2026
A39: AutoEntry (solo, per mo) | B39: 24 | C39: per-document. Source: Datamolino cmp, 2026
A40: SaaS affiliate commission norm | B40: 0.3 | C40: 20-30% std. Source: Tapfiliate, 2026
A41: AVInt Pro discount vs Dext Practice | B41: =1-B5/B36 -> 0.3220339 | C41: how much cheaper AVInt Pro is
A43: Benchmarks last verified May 2026 across multiple independent sources.

Sheet Unit Economics
A1: Unit Economics
A2: Per-customer value, acquisition-cost comparison, and reward cost-vs-value.
A4: CUSTOMER LIFETIME VALUE
A5: ARPU (Pro) | B5: =Assumptions!$B$5 -> 12 | C5: $/month (link: Assumptions)
A6: Gross margin | B6: =Assumptions!$B$13 -> 0.75 | C6: link: Assumptions
A7: Avg lifetime | B7: =Assumptions!$B$17 -> 14.285714 | C7: months (link: Assumptions)
A8: LTV — gross revenue | B8: =B5*B7 -> 171.42857 | C8: ARPU x lifetime
A9: LTV — gross profit | B9: =B8*B6 -> 128.57143 | C9: x gross margin
A10: Cash commission (standard) | B10: =Assumptions!$B$20 -> 0.3 | C10: link: Assumptions
A11: Lifetime commission paid | B11: =B8*B10 -> 51.428571 | C11: 30% recurring x LTV revenue
A12: Net gross profit after commission | B12: =B9-B11 -> 77.142857 | C12: what we keep per partner-referred customer
A14: ACQUISITION COST COMPARISON
A15: Partner CAC — upfront cash | B15: 0 | C15: commission is pay-as-you-earn (no upfront)
A16: Reference: paid-ads CAC | B16: 50 | C16: assumption, for comparison only
A17: LTV : CAC (vs paid ads) | B17: =B9/B16 -> 2.5714286 | C17: gross-profit LTV / ads CAC
A18: Partner-channel payback | B18: ~ immediate | C18: commission only paid as revenue arrives
A20: REWARD COST vs VALUE (free-access track)
A21: Milestone | B21: Active referrals | C21: Reward cost to us | D21: Revenue unlocked | E21: Cost as % of rev
A22: Free 1 month Pro | B22: =Assumptions!$B$28 -> 3 | C22: =1*$B$5*Assumptions!$B$12 -> 3 | D22: =B22*$B$8 -> 514.28571 | E22: =C22/D22 -> 0.0058333333
A23: Free 6 months Pro | B23: =Assumptions!$B$29 -> 10 | C23: =6*$B$5*Assumptions!$B$12 -> 18 | D23: =B23*$B$8 -> 1714.2857 | E23: =C23/D23 -> 0.0105
A24: Free 12 months (annual) | B24: =Assumptions!$B$30 -> 25 | C24: =12*$B$5*Assumptions!$B$12 -> 36 | D24: =B24*$B$8 -> 4285.7143 | E24: =C24/D24 -> 0.0084
A25: Take-away: free-access rewards cost ~1% of the recurring revenue they unlock.

Sheet Reward Tiers
A1: Partner Reward Tiers
A2: One program. Partners pick a track; tier rises with active paid referrals.
A4: Tier | B4: Active paid referrals | C4: Cash track (recurring) | D4: Access track reward | E4: Benefits
A5: Registered | B5: 0 – 2 | C5: =Assumptions!$B$20-0.05 -> 0.25 | D5: — | E5: Unique code/link, partner welcome kit, marketing assets
A6: Bronze | B6: 3 – 9 | C6: =Assumptions!$B$20 -> 0.3 | D6: 1 month free Pro | E6: Partner badge, onboarding help, email support
A7: Silver | B7: 10 – 24 | C7: =Assumptions!$B$20+0.05 -> 0.35 | D7: 6 months free Pro | E7: 'Find a Partner' listing, co-marketing, priority support
A8: Gold | B8: 25 + | C8: =Assumptions!$B$21 -> 0.4 | D8: 12 months free (annual) + free Pro while Gold | E8: Featured partner, dedicated manager, early access, 30% wholesale resell
A10: Partners choose Cash OR Access track. Gold earns free Pro AND a 15% cash residual.
A12: RECOMMENDED TRACK BY PARTNER TYPE
A13: Accountants & bookkeepers | B13: Access track + 30% wholesale resell (they use AVInt for clients)
A14: Business orgs & coworking | B14: Bulk Day-Pass/Gift-Code packs as member perk; Access track for the org
A15: Affiliates & creators | B15: Cash track — 30% recurring commission via unique code/link

Sheet 12-Month Scenarios
A1: 12-Month Partner-Channel Scenarios
A2: Conservative / Base / Stretch ramp. Edit yellow inputs. Churn, ARPU, GM link to Assumptions.
A4: CONSERVATIVE
A5: New partners / month | B5: 4
A6: New Pro subs / active partner / mo | B6: 1
A7: Codes sold / active partner / mo | B7: 2
A8: Blended commission rate | B8: 0.32
A10: Line / Month | C10: M1 | D10: M2 | E10: M3 | F10: M4 | G10: M5 | H10: M6 | I10: M7 | J10: M8 | K10: M9 | L10: M10 | M10: M11 | N10: M12
A11: New partners | C11: =$B$5 -> 4 | D11: =$B$5 -> 4 | E11: =$B$5 -> 4 | F11: =$B$5 -> 4 | G11: =$B$5 -> 4 | H11: =$B$5 -> 4 | I11: =$B$5 -> 4 | J11: =$B$5 -> 4 | ... N11: =$B$5 -> 4
A12: Cumulative active partners | C12: =C11 -> 4 | D12: =C12+D11 -> 8 | E12: =D12+E11 -> 12 | F12: =E12+F11 -> 16 | G12: =F12+G11 -> 20 | H12: =G12+H11 -> 24 | I12: =H12+I11 -> 28 | J12: =I12+J11 -> 32 | K12: =J12+K11 -> 36 | ... N12: =M12+N11 -> 48
A13: New Pro subs | C13: =C12*$B$6 -> 4 | D13: =D12*$B$6 -> 8 | E13: =E12*$B$6 -> 12 | F13: =F12*$B$6 -> 16 | G13: =G12*$B$6 -> 20 | H13: =H12*$B$6 -> 24 | I13: =I12*$B$6 -> 28 | J13: =J12*$B$6 -> 32 | ... N13: =N12*$B$6 -> 48
A14: Churned Pro subs | C14: 0 | D14: =C15*Assumptions!$B$16 -> 0.28 | E14: =D15*Assumptions!$B$16 -> 0.8204 | F14: =E15*Assumptions!$B$16 -> 1.602972 | G14: =F15*Assumptions!$B$16 -> 2.610764 | H14: =G15*Assumptions!$B$16 -> 3.8280105 | I14: =H15*Assumptions!$B$16 -> 5.2400497 | J14: =I15*Assumptions!$B$16 -> 6.8332463 | K14: =J15*Assumptions!$B$16 -> 8.594919 | ... N14: =M15*Assumptions!$B$16 -> 14.776931
A15: Active Pro subs (EOM) | C15: =C13 -> 4 | D15: =C15*(1-Assumptions!$B$16)+D13 -> 11.72 | E15: =D15*(1-Assumptions!$B$16)+E13 -> 22.8996 | F15: =E15*(1-Assumptions!$B$16)+F13 -> 37.296628 | G15: =F15*(1-Assumptions!$B$16)+G13 -> 54.685864 | H15: =G15*(1-Assumptions!$B$16)+H13 -> 74.857854 | I15: =H15*(1-Assumptions!$B$16)+I13 -> 97.617804 | J15: =I15*(1-Assumptions!$B$16)+J13 -> 122.78456 | K15: =J15*(1-Assumptions!$B$16)+K13 -> 150.18964 | ... N15: =M15*(1-Assumptions!$B$16)+N13 -> 244.32209
A16: Pro MRR | C16: =C15*Assumptions!$B$5 -> 48 | D16: =D15*Assumptions!$B$5 -> 140.64 | E16: =E15*Assumptions!$B$5 -> 274.7952 | F16: =F15*Assumptions!$B$5 -> 447.55954 | G16: =G15*Assumptions!$B$5 -> 656.23037 | H16: =H15*Assumptions!$B$5 -> 898.29424 | I16: =I15*Assumptions!$B$5 -> 1171.4136 | J16: =J15*Assumptions!$B$5 -> 1473.4147 | ... N16: =N15*Assumptions!$B$5 -> 2931.865
A17: Codes sold | C17: =C12*$B$7 -> 8 | D17: =D12*$B$7 -> 16 | E17: =E12*$B$7 -> 24 | F17: =F12*$B$7 -> 32 | G17: =G12*$B$7 -> 40 | H17: =H12*$B$7 -> 48 | I17: =I12*$B$7 -> 56 | J17: =J12*$B$7 -> 64 | ... N17: =N12*$B$7 -> 96
A18: Day-pass revenue | C18: =C17*Assumptions!$B$9 -> 48 | D18: =D17*Assumptions!$B$9 -> 96 | E18: =E17*Assumptions!$B$9 -> 144 | F18: =F17*Assumptions!$B$9 -> 192 | G18: =G17*Assumptions!$B$9 -> 240 | H18: =H17*Assumptions!$B$9 -> 288 | I18: =I17*Assumptions!$B$9 -> 336 | J18: =J17*Assumptions!$B$9 -> 384 | ... N18: =N17*Assumptions!$B$9 -> 576
A19: Commission paid | C19: =(C16+C18)*$B$8 -> 30.72 | D19: =(D16+D18)*$B$8 -> 75.7248 | E19: =(E16+E18)*$B$8 -> 134.01446 | F19: =(F16+F18)*$B$8 -> 204.65905 | G19: =(G16+G18)*$B$8 -> 286.79372 | H19: =(H16+H18)*$B$8 -> 379.61416 | I19: =(I16+I18)*$B$8 -> 482.37237 | J19: =(J16+J18)*$B$8 -> 594.3727 | ... N19: =(N16+N18)*$B$8 -> 1122.5168
A20: Net contribution | C20: =(C16+C18)*Assumptions!$B$13-C19 -> 41.28 | D20: =(D16+D18)*Assumptions!$B$13-D19 -> 101.7552 | E20: =(E16+E18)*Assumptions!$B$13-E19 -> 180.08194 | F20: =(F16+F18)*Assumptions!$B$13-F19 -> 275.0106 | G20: =(G16+G18)*Assumptions!$B$13-G19 -> 385.37906 | H20: =(H16+H18)*Assumptions!$B$13-H19 -> 510.10652 | I20: =(I16+I18)*Assumptions!$B$13-I19 -> 648.18787 | J20: =(J16+J18)*Assumptions!$B$13-J19 -> 798.68832 | ... N20: =(N16+N18)*Assumptions!$B$13-N19 -> 1508.382
A22: Active Pro subs (M12) | B22: =N15 -> 244.32209
A23: MRR (M12) | B23: =N16 -> 2931.865
A24: ARR (M12) | B24: =N16*12 -> 35182.381
A25: Cumulative Pro revenue (12 mo) | B25: =SUM(C16:N16) -> 14533.793
A26: Cumulative day-pass revenue | B26: =SUM(C18:N18) -> 3744
A27: Cumulative commission paid | B27: =SUM(C19:N19) -> 5848.8938
A28: Cumulative net contribution | B28: =SUM(C20:N20) -> 7859.451
A31: BASE
A32: New partners / month | B32: 8
A33: New Pro subs / active partner / mo | B33: 1.5
A34: Codes sold / active partner / mo | B34: 4
A35: Blended commission rate | B35: 0.32
A37: Line / Month | C37: M1 | D37: M2 | E37: M3 | F37: M4 | G37: M5 | H37: M6 | I37: M7 | J37: M8 | K37: M9 | L37: M10 | M37: M11 | N37: M12
A38: New partners | C38: =$B$32 -> 8 | D38: =$B$32 -> 8 | E38: =$B$32 -> 8 | F38: =$B$32 -> 8 | G38: =$B$32 -> 8 | H38: =$B$32 -> 8 | I38: =$B$32 -> 8 | J38: =$B$32 -> 8 | ... N38: =$B$32 -> 8
A39: Cumulative active partners | C39: =C38 -> 8 | D39: =C39+D38 -> 16 | E39: =D39+E38 -> 24 | F39: =E39+F38 -> 32 | G39: =F39+G38 -> 40 | H39: =G39+H38 -> 48 | I39: =H39+I38 -> 56 | J39: =I39+J38 -> 64 | K39: =J39+K38 -> 72 | ... N39: =M39+N38 -> 96
A40: New Pro subs | C40: =C39*$B$33 -> 12 | D40: =D39*$B$33 -> 24 | E40: =E39*$B$33 -> 36 | F40: =F39*$B$33 -> 48 | G40: =G39*$B$33 -> 60 | H40: =H39*$B$33 -> 72 | I40: =I39*$B$33 -> 84 | J40: =J39*$B$33 -> 96 | ... N40: =N39*$B$33 -> 144
A41: Churned Pro subs | C41: 0 | D41: =C42*Assumptions!$B$16 -> 0.84 | E41: =D42*Assumptions!$B$16 -> 2.4612 | F41: =E42*Assumptions!$B$16 -> 4.808916 | G41: =F42*Assumptions!$B$16 -> 7.8322919 | H41: =G42*Assumptions!$B$16 -> 11.484031 | I41: =H42*Assumptions!$B$16 -> 15.720149 | J41: =I42*Assumptions!$B$16 -> 20.499739 | K41: =J42*Assumptions!$B$16 -> 25.784757 | ... N41: =M42*Assumptions!$B$16 -> 44.330794
A42: Active Pro subs (EOM) | C42: =C40 -> 12 | D42: =C42*(1-Assumptions!$B$16)+D40 -> 35.16 | E42: =D42*(1-Assumptions!$B$16)+E40 -> 68.6988 | F42: =E42*(1-Assumptions!$B$16)+F40 -> 111.88988 | G42: =F42*(1-Assumptions!$B$16)+G40 -> 164.05759 | H42: =G42*(1-Assumptions!$B$16)+H40 -> 224.57356 | I42: =H42*(1-Assumptions!$B$16)+I40 -> 292.85341 | J42: =I42*(1-Assumptions!$B$16)+J40 -> 368.35367 | K42: =J42*(1-Assumptions!$B$16)+K40 -> 450.56892 | ... N42: =M42*(1-Assumptions!$B$16)+N40 -> 732.96626
A43: Pro MRR | C43: =C42*Assumptions!$B$5 -> 144 | D43: =D42*Assumptions!$B$5 -> 421.92 | E43: =E42*Assumptions!$B$5 -> 824.3856 | F43: =F42*Assumptions!$B$5 -> 1342.6786 | G43: =G42*Assumptions!$B$5 -> 1968.6911 | H43: =H42*Assumptions!$B$5 -> 2694.8827 | I43: =I42*Assumptions!$B$5 -> 3514.2409 | J43: =J42*Assumptions!$B$5 -> 4420.2441 | ... N43: =N42*Assumptions!$B$5 -> 8795.5951
A44: Codes sold | C44: =C39*$B$34 -> 32 | D44: =D39*$B$34 -> 64 | E44: =E39*$B$34 -> 96 | F44: =F39*$B$34 -> 128 | G44: =G39*$B$34 -> 160 | H44: =H39*$B$34 -> 192 | I44: =I39*$B$34 -> 224 | J44: =J39*$B$34 -> 256 | ... N44: =N39*$B$34 -> 384
A45: Day-pass revenue | C45: =C44*Assumptions!$B$9 -> 192 | D45: =D44*Assumptions!$B$9 -> 384 | E45: =E44*Assumptions!$B$9 -> 576 | F45: =F44*Assumptions!$B$9 -> 768 | G45: =G44*Assumptions!$B$9 -> 960 | H45: =H44*Assumptions!$B$9 -> 1152 | I45: =I44*Assumptions!$B$9 -> 1344 | J45: =J44*Assumptions!$B$9 -> 1536 | ... N45: =N44*Assumptions!$B$9 -> 2304
A46: Commission paid | C46: =(C43+C45)*$B$35 -> 107.52 | D46: =(D43+D45)*$B$35 -> 257.8944 | E46: =(E43+E45)*$B$35 -> 448.12339 | F46: =(F43+F45)*$B$35 -> 675.41715 | G46: =(G43+G45)*$B$35 -> 937.18115 | H46: =(H43+H45)*$B$35 -> 1231.0025 | I46: =(I43+I45)*$B$35 -> 1554.6371 | J46: =(J43+J45)*$B$35 -> 1905.9981 | ... N46: =(N43+N45)*$B$35 -> 3551.8704
A47: Net contribution | C47: =(C43+C45)*Assumptions!$B$13-C46 -> 144.48 | D47: =(D43+D45)*Assumptions!$B$13-D46 -> 346.5456 | E47: =(E43+E45)*Assumptions!$B$13-E46 -> 602.16581 | F47: =(F43+F45)*Assumptions!$B$13-F46 -> 907.5918 | G47: =(G43+G45)*Assumptions!$B$13-G46 -> 1259.3372 | H47: =(H43+H45)*Assumptions!$B$13-H46 -> 1654.1596 | I47: =(I43+I45)*Assumptions!$B$13-I46 -> 2089.0436 | J47: =(J43+J45)*Assumptions!$B$13-J46 -> 2561.185 | ... N47: =(N43+N45)*Assumptions!$B$13-N46 -> 4772.8259
A49: Active Pro subs (M12) | B49: =N42 -> 732.96626
A50: MRR (M12) | B50: =N43 -> 8795.5951
A51: ARR (M12) | B51: =N43*12 -> 105547.14
A52: Cumulative Pro revenue (12 mo) | B52: =SUM(C43:N43) -> 43601.379
A53: Cumulative day-pass revenue | B53: =SUM(C45:N45) -> 14976
A54: Cumulative commission paid | B54: =SUM(C46:N46) -> 18744.761
A55: Cumulative net contribution | B55: =SUM(C47:N47) -> 25188.273
A58: STRETCH
A59: New partners / month | B59: 15
A60: New Pro subs / active partner / mo | B60: 2.5
A61: Codes sold / active partner / mo | B61: 8
A62: Blended commission rate | B62: 0.33
A64: Line / Month | C64: M1 | D64: M2 | E64: M3 | F64: M4 | G64: M5 | H64: M6 | I64: M7 | J64: M8 | K64: M9 | L64: M10 | M64: M11 | N64: M12
A65: New partners | C65: =$B$59 -> 15 | D65: =$B$59 -> 15 | E65: =$B$59 -> 15 | F65: =$B$59 -> 15 | G65: =$B$59 -> 15 | H65: =$B$59 -> 15 | I65: =$B$59 -> 15 | J65: =$B$59 -> 15 | ... N65: =$B$59 -> 15
A66: Cumulative active partners | C66: =C65 -> 15 | D66: =C66+D65 -> 30 | E66: =D66+E65 -> 45 | F66: =E66+F65 -> 60 | G66: =F66+G65 -> 75 | H66: =G66+H65 -> 90 | I66: =H66+I65 -> 105 | J66: =I66+J65 -> 120 | K66: =J66+K65 -> 135 | ... N66: =M66+N65 -> 180
A67: New Pro subs | C67: =C66*$B$60 -> 37.5 | D67: =D66*$B$60 -> 75 | E67: =E66*$B$60 -> 112.5 | F67: =F66*$B$60 -> 150 | G67: =G66*$B$60 -> 187.5 | H67: =H66*$B$60 -> 225 | I67: =I66*$B$60 -> 262.5 | J67: =J66*$B$60 -> 300 | ... N67: =N66*$B$60 -> 450
A68: Churned Pro subs | C68: 0 | D68: =C69*Assumptions!$B$16 -> 2.625 | E68: =D69*Assumptions!$B$16 -> 7.69125 | F68: =E69*Assumptions!$B$16 -> 15.027862 | G68: =F69*Assumptions!$B$16 -> 24.475912 | H68: =G69*Assumptions!$B$16 -> 35.887598 | I68: =H69*Assumptions!$B$16 -> 49.125466 | J68: =I69*Assumptions!$B$16 -> 64.061684 | K68: =J69*Assumptions!$B$16 -> 80.577366 | ... N68: =M69*Assumptions!$B$16 -> 138.53373
A69: Active Pro subs (EOM) | C69: =C67 -> 37.5 | D69: =C69*(1-Assumptions!$B$16)+D67 -> 109.875 | E69: =D69*(1-Assumptions!$B$16)+E67 -> 214.68375 | F69: =E69*(1-Assumptions!$B$16)+F67 -> 349.65589 | G69: =F69*(1-Assumptions!$B$16)+G67 -> 512.67998 | H69: =G69*(1-Assumptions!$B$16)+H67 -> 701.79238 | I69: =H69*(1-Assumptions!$B$16)+I67 -> 915.16691 | J69: =I69*(1-Assumptions!$B$16)+J67 -> 1151.1052 | K69: =J69*(1-Assumptions!$B$16)+K67 -> 1408.0279 | ... N69: =M69*(1-Assumptions!$B$16)+N67 -> 2290.5196
A70: Pro MRR | C70: =C69*Assumptions!$B$5 -> 450 | D70: =D69*Assumptions!$B$5 -> 1318.5 | E70: =E69*Assumptions!$B$5 -> 2576.205 | F70: =F69*Assumptions!$B$5 -> 4195.8706 | G70: =G69*Assumptions!$B$5 -> 6152.1597 | H70: =H69*Assumptions!$B$5 -> 8421.5085 | I70: =I69*Assumptions!$B$5 -> 10982.003 | J70: =J69*Assumptions!$B$5 -> 13813.263 | ... N70: =N69*Assumptions!$B$5 -> 27486.235
A71: Codes sold | C71: =C66*$B$61 -> 120 | D71: =D66*$B$61 -> 240 | E71: =E66*$B$61 -> 360 | F71: =F66*$B$61 -> 480 | G71: =G66*$B$61 -> 600 | H71: =H66*$B$61 -> 720 | I71: =I66*$B$61 -> 840 | J71: =J66*$B$61 -> 960 | ... N71: =N66*$B$61 -> 1440
A72: Day-pass revenue | C72: =C71*Assumptions!$B$9 -> 720 | D72: =D71*Assumptions!$B$9 -> 1440 | E72: =E71*Assumptions!$B$9 -> 2160 | F72: =F71*Assumptions!$B$9 -> 2880 | G72: =G71*Assumptions!$B$9 -> 3600 | H72: =H71*Assumptions!$B$9 -> 4320 | I72: =I71*Assumptions!$B$9 -> 5040 | J72: =J71*Assumptions!$B$9 -> 5760 | ... N72: =N71*Assumptions!$B$9 -> 8640
A73: Commission paid | C73: =(C70+C72)*$B$62 -> 386.1 | D73: =(D70+D72)*$B$62 -> 910.305 | E73: =(E70+E72)*$B$62 -> 1562.9477 | F73: =(F70+F72)*$B$62 -> 2335.0373 | G73: =(G70+G72)*$B$62 -> 3218.2127 | H73: =(H70+H72)*$B$62 -> 4204.6978 | I73: =(I70+I72)*$B$62 -> 5287.261 | J73: =(J70+J72)*$B$62 -> 6459.1767 | ... N73: =(N70+N72)*$B$62 -> 11921.657
A74: Net contribution | C74: =(C70+C72)*Assumptions!$B$13-C73 -> 491.4 | D74: =(D70+D72)*Assumptions!$B$13-D73 -> 1158.57 | E74: =(E70+E72)*Assumptions!$B$13-E73 -> 1989.2061 | F74: =(F70+F72)*Assumptions!$B$13-F73 -> 2971.8657 | G74: =(G70+G72)*Assumptions!$B$13-G73 -> 4095.9071 | H74: =(H70+H72)*Assumptions!$B$13-H73 -> 5351.4336 | I74: =(I70+I72)*Assumptions!$B$13-I73 -> 6729.2412 | J74: =(J70+J72)*Assumptions!$B$13-J73 -> 8220.7703 | ... N74: =(N70+N72)*Assumptions!$B$13-N73 -> 15173.019
A76: Active Pro subs (M12) | B76: =N69 -> 2290.5196
A77: MRR (M12) | B77: =N70 -> 27486.235
A78: ARR (M12) | B78: =N70*12 -> 329834.82
A79: Cumulative Pro revenue (12 mo) | B79: =SUM(C70:N70) -> 136254.31
A80: Cumulative day-pass revenue | B80: =SUM(C72:N72) -> 56160
A81: Cumulative commission paid | B81: =SUM(C73:N73) -> 63496.722
A82: Cumulative net contribution | B82: =SUM(C74:N74) -> 80814.01
